gradio_networkgraph/__init__.py
gradio_networkgraph/networkgraph.py
gradio_networkgraph/networkgraph.pyi
gradio_networkgraph/templates/component/index.js
gradio_networkgraph/templates/component/style.css
gradio_networkgraph/templates/example/index.js
gradio_networkgraph/templates/example/style.css
gradio_networkgraph-0.0.3.dist-info/METADATA
gradio_networkgraph-0.0.3.dist-info/WHEEL
gradio_networkgraph-0.0.3.dist-info/RECORD
